mily/__init__.py
mily/_version.py
mily/tests/__init__.py
mily/tests/conftest.py
mily/tests/test_examples.py
mily-0.0.1rc1.dist-info/DESCRIPTION.rst
mily-0.0.1rc1.dist-info/METADATA
mily-0.0.1rc1.dist-info/RECORD
mily-0.0.1rc1.dist-info/WHEEL
mily-0.0.1rc1.dist-info/entry_points.txt
mily-0.0.1rc1.dist-info/metadata.json
mily-0.0.1rc1.dist-info/top_level.txt
