Metadata-Version: 2.0
Name: mily
Version: 0.0.1rc1
Summary: A collection of Qt building blocks for scientific GUIs.
Home-page: https://github.com/NSLS-II/mily
Author: Brookhaven National Lab
Author-email: tcaswell@bnl.gov
License: BSD (3-clause)
Platform: UNKNOWN
Classifier: Development Status :: 2 - Pre-Alpha
Classifier: Natural Language :: English
Classifier: Programming Language :: Python :: 3
